induction/app.py
induction/encoding.py
induction/utils.py
induction/response.py
induction/request.py
induction/protocol.py
induction/__init__.py
induction-0.2.dist-info/RECORD
induction-0.2.dist-info/top_level.txt
induction-0.2.dist-info/WHEEL
induction-0.2.dist-info/DESCRIPTION.rst
induction-0.2.dist-info/metadata.json
induction-0.2.dist-info/METADATA
