Metadata-Version: 2.0
Name: induction
Version: 0.2
Summary: A simple web framework based on asyncio.
Home-page: UNKNOWN
Author: Bruno Renié
Author-email: bruno@renie.fr
License: UNKNOWN
Platform: UNKNOWN
Classifier: Environment :: Web Environment
Classifier: Intended Audience :: Developers
Classifier: License :: OSI Approved :: BSD License
Classifier: Programming Language :: Python
Classifier: Programming Language :: Python :: 3
Classifier: Programming Language :: Python :: 3.3
Classifier: Programming Language :: Python :: 3.4
Requires-Dist: Jinja2
Requires-Dist: Routes
Requires-Dist: aiohttp
Requires-Dist: asyncio
